sigma_koki.py
pysigmakoki-2.1.9.dist-info/METADATA
pysigmakoki-2.1.9.dist-info/WHEEL
pysigmakoki-2.1.9.dist-info/top_level.txt
pysigmakoki-2.1.9.dist-info/RECORD
