Metadata-Version: 2.4
Name: PySigmaKoki
Version: 2.1.9
Summary: Python Interface for Instruments by Sigma Koki
Author-email: Akira Okumura <oxon@mac.com>
License: BSD License
Project-URL: Repository, https://github.com/akira-okumura/PySigmaKoki.git
Project-URL: Issues, https://github.com/akira-okumura/PySigmaKoki/issues
Classifier: Programming Language :: Python :: 3
Classifier: License :: OSI Approved :: BSD License
Classifier: Operating System :: OS Independent
Requires-Dist: pyserial
